cow_download/__init__.py
cow_download/cow_download.py
cow_download/main.py
cow_download-0.0.8.dist-info/METADATA
cow_download-0.0.8.dist-info/WHEEL
cow_download-0.0.8.dist-info/entry_points.txt
cow_download-0.0.8.dist-info/top_level.txt
cow_download-0.0.8.dist-info/RECORD
