Metadata-Version: 2.1
Name: cow-download
Version: 0.0.8
Summary: Easily downlaod file from cow transfer
Home-page: https://github.com/txbhandsome/cow_download.git
Author: txb
Author-email: txb.sdn@gmail.com
License: MIT
Keywords: python,DownloadKit,cow_download
Platform: UNKNOWN
Classifier: Development Status :: 3 - Alpha
Classifier: Intended Audience :: Developers
Classifier: Programming Language :: Python :: 3
Classifier: Operating System :: Microsoft :: Windows
Requires-Dist: DownloadKit
Requires-Dist: requests
